setup.py
fake/__init__.py
fake/api.py
fake/context_managers.py
fake/decorators.py
fake/operations.py
fake/state.py
fake/utils.py
fake.egg-info/PKG-INFO
fake.egg-info/SOURCES.txt
fake.egg-info/dependency_links.txt
fake.egg-info/requires.txt
fake.egg-info/top_level.txt
fake/scm/__init__.py
fake/scm/base.py
fake/scm/git.py
fake/tasks/__init__.py
fake/tasks/deploy.py
fake/tasks/framework.py
fake/tasks/helpers.py