Metadata-Version: 1.1
Name: fake
Version: 0.4
Summary: Make Python's Fabric act like Ruby's Capistrano
Home-page: http://github.com/bmuller/fake
Author: Brian Muller
Author-email: bamuller@gmail.com
License: MIT
Platform: UNKNOWN
Requires: fabric
